finnhub/__init__.py
finnhub/client.py
finnhub/exceptions.py
finnhub_python-2.4.20.dist-info/LICENSE
finnhub_python-2.4.20.dist-info/METADATA
finnhub_python-2.4.20.dist-info/WHEEL
finnhub_python-2.4.20.dist-info/top_level.txt
finnhub_python-2.4.20.dist-info/RECORD
