Metadata-Version: 2.1
Name: finnhub-python
Version: 2.4.20
Summary: Finnhub API
Home-page: https://finnhub.io/docs/api
Author: Finnhub
Author-email: support@finnhub.io
License: Apache-2.0
Keywords: finnhub,Finnhub API,api
License-File: LICENSE
Requires-Dist: requests>=2.22.0
